README.rst
setup.py
fabdeploit/__init__.py
fabdeploit/base.py
fabdeploit/django.py
fabdeploit/drupal.py
fabdeploit/git.py
fabdeploit/magento.py
fabdeploit/uploader.py
fabdeploit/utils.py
fabdeploit/virtualenv.py
fabdeploit.egg-info/PKG-INFO
fabdeploit.egg-info/SOURCES.txt
fabdeploit.egg-info/dependency_links.txt
fabdeploit.egg-info/not-zip-safe
fabdeploit.egg-info/requires.txt
fabdeploit.egg-info/top_level.txt